`Heilo.java`：

```java
package com.zgkaii.jvm.misson.misson1;

public class Hello {
    private static int[] numbers = {1, 6, 8};

    public static void main(String[] args) {
        MovingAverage ma = new MovingAverage();
        int num1 = 1;
        int num2 = 2;
        ma.submit(num1);
        ma.submit(num2);
        double avg1 = ma.getAvg();

        MovingAverage mb = new MovingAverage();
        for (int number : numbers) {
            mb.submit(number);
        }
        double avg2 = mb.getAvg();
    }
}

class MovingAverage {
    private int count = 0;
    private double sum = 0.0D;

    public void submit(double value) {
        this.count++;
        this.sum += value;
    }

    public double getAvg() {
        if (0 == this.count) {
            return sum;
        }
        return this.sum / this.count;
    }
}
```

`Heilo.java`生成的字节码文件：`javac Hello.java`

`Hello.class`：

```java
//
// Source code recreated from a .class file by IntelliJ IDEA
// (powered by Fernflower decompiler)
//

package com.zgkaii.jvm.misson.misson1;

public class Hello {
    private static int[] numbers = new int[]{1, 6, 8};

    public Hello() {
    }

    public static void main(String[] var0) {
        MovingAverage var1 = new MovingAverage();
        byte var2 = 1;
        byte var3 = 2;
        var1.submit((double)var2);
        var1.submit((double)var3);
        double var4 = var1.getAvg();
        MovingAverage var6 = new MovingAverage();
        int[] var7 = numbers;
        int var8 = var7.length;

        for(int var9 = 0; var9 < var8; ++var9) {
            int var10 = var7[var9];
            var6.submit((double)var10);
        }

        double var11 = var6.getAvg();
    }
}
```

`MovingAverage.class`：

```java
//
// Source code recreated from a .class file by IntelliJ IDEA
// (powered by Fernflower decompiler)
//

package com.zgkaii.jvm.misson.misson1;

class MovingAverage {
    private int count = 0;
    private double sum = 0.0D;

    MovingAverage() {
    }

    public void submit(double var1) {
        ++this.count;
        this.sum += var1;
    }

    public double getAvg() {
        return 0 == this.count ? this.sum : this.sum / (double)this.count;
    }
}
```

反编译class文件：`javap -c -v Hello`

```java
Classfile xxx/Hello.class
  Last modified 2021-3-21; size 703 bytes
  MD5 checksum ebef6b39d6fe37ead14ab91b5ae6a849
  Compiled from "Hello.java"
public class com.zgkaii.jvm.misson.misson1.Hello
  minor version: 0
  major version: 55						  // 
  flags: ACC_PUBLIC, ACC_SUPER
Constant pool:
   #1 = Methodref          #8.#23         // java/lang/Object."<init>":()V
   #2 = Class              #24            // com/zgkaii/jvm/misson/misson1/MovingAverage
   #3 = Methodref          #2.#23         // com/zgkaii/jvm/misson/misson1/MovingAverage."<init>":()V
   #4 = Methodref          #2.#25         // com/zgkaii/jvm/misson/misson1/MovingAverage.submit:(D)V
   #5 = Methodref          #2.#26         // com/zgkaii/jvm/misson/misson1/MovingAverage.getAvg:()D
   #6 = Fieldref           #7.#27         // com/zgkaii/jvm/misson/misson1/Hello.numbers:[I
   #7 = Class              #28            // com/zgkaii/jvm/misson/misson1/Hello
   #8 = Class              #29            // java/lang/Object
   #9 = Utf8               numbers
  #10 = Utf8               [I
  #11 = Utf8               <init>
  #12 = Utf8               ()V
  #13 = Utf8               Code
  #14 = Utf8               LineNumberTable
  #15 = Utf8               main
  #16 = Utf8               ([Ljava/lang/String;)V
  #17 = Utf8               StackMapTable
  #18 = Class              #30            // "[Ljava/lang/String;"
  #19 = Class              #10            // "[I"
  #20 = Utf8               <clinit>
  #21 = Utf8               SourceFile
  #22 = Utf8               Hello.java
  #23 = NameAndType        #11:#12        // "<init>":()V
  #24 = Utf8               com/zgkaii/jvm/misson/misson1/MovingAverage
  #25 = NameAndType        #31:#32        // submit:(D)V
  #26 = NameAndType        #33:#34        // getAvg:()D
  #27 = NameAndType        #9:#10         // numbers:[I
  #28 = Utf8               com/zgkaii/jvm/misson/misson1/Hello
  #29 = Utf8               java/lang/Object
  #30 = Utf8               [Ljava/lang/String;
  #31 = Utf8               submit
  #32 = Utf8               (D)V
  #33 = Utf8               getAvg
  #34 = Utf8               ()D
{
  public com.zgkaii.jvm.misson.misson1.Hello();
    descriptor: ()V
    flags: ACC_PUBLIC
    Code:
      stack=1, locals=1, args_size=1
         0: aload_0
         1: invokespecial #1                  // Method java/lang/Object."<init>":()V
         4: return
      LineNumberTable:
        line 3: 0

  public static void main(java.lang.String[]);
    descriptor: ([Ljava/lang/String;)V
    flags: ACC_PUBLIC, ACC_STATIC
    Code:
      stack=3, locals=11, args_size=1
         0: new           #2                  // class com/zgkaii/jvm/misson/misson1/MovingAverage
         3: dup
         4: invokespecial #3                  // Method com/zgkaii/jvm/misson/misson1/MovingAverage."<init>":()V
         7: astore_1
         8: iconst_1
         9: istore_2
        10: iconst_2
        11: istore_3
        12: aload_1
        13: iload_2
        14: i2d
        15: invokevirtual #4                  // Method com/zgkaii/jvm/misson/misson1/MovingAverage.submit:(D)V
        18: aload_1
        19: iload_3
        20: i2d
        21: invokevirtual #4                  // Method com/zgkaii/jvm/misson/misson1/MovingAverage.submit:(D)V
        24: aload_1
        25: invokevirtual #5                  // Method com/zgkaii/jvm/misson/misson1/MovingAverage.getAvg:()D
        28: dstore        4
        30: new           #2                  // class com/zgkaii/jvm/misson/misson1/MovingAverage
        33: dup
        34: invokespecial #3                  // Method com/zgkaii/jvm/misson/misson1/MovingAverage."<init>":()V
        37: astore        6
        39: getstatic     #6                  // Field numbers:[I
        42: astore        7
        44: aload         7
        46: arraylength
        47: istore        8
        49: iconst_0
        50: istore        9
        52: iload         9
        54: iload         8
        56: if_icmpge     80
        59: aload         7
        61: iload         9
        63: iaload
        64: istore        10
        66: aload         6
        68: iload         10
        70: i2d
        71: invokevirtual #4                  // Method com/zgkaii/jvm/misson/misson1/MovingAverage.submit:(D)V
        74: iinc          9, 1
        77: goto          52
        80: aload         6
        82: invokevirtual #5                  // Method com/zgkaii/jvm/misson/misson1/MovingAverage.getAvg:()D
        85: dstore        7
        87: return
      LineNumberTable:
        line 7: 0
        line 8: 8
        line 9: 10
        line 10: 12
        line 11: 18
        line 12: 24
        line 14: 30
        line 15: 39
        line 16: 66
        line 15: 74
        line 18: 80
        line 19: 87
      StackMapTable: number_of_entries = 2
        frame_type = 255 /* full_frame */
          offset_delta = 52
          locals = [ class "[Ljava/lang/String;", class com/zgkaii/jvm/misson/misson1/MovingAverage, int, int, double, class com/zgkaii/jvm/misson/misson1/MovingAverage, class "[I", in
t, int ]
          stack = []
        frame_type = 248 /* chop */
          offset_delta = 27

  static {};
    descriptor: ()V
    flags: ACC_STATIC
    Code:
      stack=4, locals=0, args_size=0
         0: iconst_3
         1: newarray       int
         3: dup
         4: iconst_0
         5: iconst_1
         6: iastore
         7: dup
         8: iconst_1
         9: bipush        6
        11: iastore
        12: dup
        13: iconst_2
        14: bipush        8
        16: iastore
        17: putstatic     #6                  // Field numbers:[I
        20: return
      LineNumberTable:
        line 4: 0
}
SourceFile: "Hello.java"
```